db2ls/.DS_Store
db2ls/.git/COMMIT_EDITMSG
db2ls/.git/FETCH_HEAD
db2ls/.git/HEAD
db2ls/.git/config
db2ls/.git/description
db2ls/.git/hooks/applypatch-msg.sample
db2ls/.git/hooks/commit-msg.sample
db2ls/.git/hooks/fsmonitor-watchman.sample
db2ls/.git/hooks/post-update.sample
db2ls/.git/hooks/pre-applypatch.sample
db2ls/.git/hooks/pre-commit.sample
db2ls/.git/hooks/pre-merge-commit.sample
db2ls/.git/hooks/pre-push.sample
db2ls/.git/hooks/pre-rebase.sample
db2ls/.git/hooks/pre-receive.sample
db2ls/.git/hooks/prepare-commit-msg.sample
db2ls/.git/hooks/push-to-checkout.sample
db2ls/.git/hooks/sendemail-validate.sample
db2ls/.git/hooks/update.sample
db2ls/.git/index
db2ls/.git/info/exclude
db2ls/.git/logs/HEAD
db2ls/.git/logs/refs/heads/main
db2ls/.git/logs/refs/remotes/origin/HEAD
db2ls/.git/logs/refs/remotes/origin/main
db2ls/.git/objects/00/ecdaa981d21a227aaaaa641cb3b2b450f1a64f
db2ls/.git/objects/05/a36ee582ef4e199f9fc92ba97eb09ea408eea4
db2ls/.git/objects/27/be6504ef1ca0706bcc49d25f4e46349ee63613
db2ls/.git/objects/36/014f3d5a22121c26dd51b6500d51e2b1b682ea
db2ls/.git/objects/41/ee02249ce68bc7dce0ac73a58e13f97f3cb5bd
db2ls/.git/objects/50/08ddfcf53c02e82d7eee2e57c38e5672ef89f6
db2ls/.git/objects/52/a082b7d69f6e86731a685fef21208cde94f85c
db2ls/.git/objects/7d/2348737e283b9c72ca767fe57902e5bf1c65a6
db2ls/.git/objects/8f/05787a35781534e9ba769c2f25c7c1936ab77c
db2ls/.git/objects/8f/d201f23477e626726b2bcdf514cc95c543fa84
db2ls/.git/objects/a3/6782e4d69fa1572c648e79580bde4356297ce4
db2ls/.git/objects/ae/d97068c8a600b35c5dba23bd8f5aa6b2204664
db2ls/.git/objects/b0/9cd7856d58590578ee1a4f3ad45d1310a97f87
db2ls/.git/objects/bc/56e2e40e5d1a5c9ffa9f8d200045cd883a5ac7
db2ls/.git/objects/be/ecce45da41c841294d314f8ac92a5d715a7f54
db2ls/.git/objects/d3/cf56c0a624d92bcf246bfa09331c111c182f94
db2ls/.git/objects/df/e0770424b2a19faf507a501ebfc23be8f54e7b
db2ls/.git/objects/f3/87874d7cae7b22eec5c94a71be76205e242ade
db2ls/.git/objects/f9/817182f84166e3f063a2754adde8fd00b140e4
db2ls-0.1.3.dist-info/LICENSE
db2ls-0.1.3.dist-info/METADATA
db2ls-0.1.3.dist-info/WHEEL
db2ls-0.1.3.dist-info/RECORD
