Metadata-Version: 2.1
Name: db2ls
Version: 0.1.3
Summary: use python to handle SQL
Author: Jianfeng
Author-email: Jianfeng.Liu0413@gmail.com
Requires-Python: >=3.12,<4.0
Classifier: Programming Language :: Python :: 3
Classifier: Programming Language :: Python :: 3.12
